odoo9_addon_l10n_ec_ote-9.0.1.0.0-py2.7-nspkg.pth
odoo_addons/l10n_ec_ote/__openerp__.py
odoo_addons/l10n_ec_ote/__init__.py
odoo_addons/l10n_ec_ote/README.rst
odoo_addons/l10n_ec_ote/security/ir.model.access.csv
odoo_addons/l10n_ec_ote/models/res_partner.py
odoo_addons/l10n_ec_ote/models/__init__.py
odoo_addons/l10n_ec_ote/models/res_company.py
odoo_addons/l10n_ec_ote/models/ote.py
odoo_addons/l10n_ec_ote/views/res_partner.xml
odoo_addons/l10n_ec_ote/views/res_company.xml
odoo_addons/l10n_ec_ote/data/res.country.state.csv
odoo_addons/l10n_ec_ote/data/l10n_ec_ote.canton.csv
odoo_addons/l10n_ec_ote/data/l10n_ec_ote.parish.csv
odoo_addons/l10n_ec_ote/data/res_country.xml
odoo_addons/l10n_ec_ote/static/description/icon.png
odoo9_addon_l10n_ec_ote-9.0.1.0.0.dist-info/top_level.txt
odoo9_addon_l10n_ec_ote-9.0.1.0.0.dist-info/WHEEL
odoo9_addon_l10n_ec_ote-9.0.1.0.0.dist-info/RECORD
odoo9_addon_l10n_ec_ote-9.0.1.0.0.dist-info/metadata.json
odoo9_addon_l10n_ec_ote-9.0.1.0.0.dist-info/DESCRIPTION.rst
odoo9_addon_l10n_ec_ote-9.0.1.0.0.dist-info/METADATA
odoo9_addon_l10n_ec_ote-9.0.1.0.0.dist-info/namespace_packages.txt
